scholar_flux/__init__.py
scholar_flux/api/__init__.py
scholar_flux/api/base_api.py
scholar_flux/api/base_coordinator.py
scholar_flux/api/models/__init__.py
scholar_flux/api/models/api_parameters.py
scholar_flux/api/models/base_parameters.py
scholar_flux/api/models/base_provider_dict.py
scholar_flux/api/models/provider_config.py
scholar_flux/api/models/provider_registry.py
scholar_flux/api/models/rate_limiter_registry.py
scholar_flux/api/models/reconstructed_response.py
scholar_flux/api/models/response_history.py
scholar_flux/api/models/response_metadata_map.py
scholar_flux/api/models/response_types.py
scholar_flux/api/models/responses.py
scholar_flux/api/models/search_api_config.py
scholar_flux/api/models/search_inputs.py
scholar_flux/api/models/search_results.py
scholar_flux/api/multisearch_coordinator.py
scholar_flux/api/normalization/__init__.py
scholar_flux/api/normalization/academic_field_map.py
scholar_flux/api/normalization/arxiv_field_map.py
scholar_flux/api/normalization/base_field_map.py
scholar_flux/api/normalization/core_field_map.py
scholar_flux/api/normalization/crossref_field_map.py
scholar_flux/api/normalization/normalizing_field_map.py
scholar_flux/api/normalization/open_alex_field_map.py
scholar_flux/api/normalization/plos_field_map.py
scholar_flux/api/normalization/pubmed_efetch_field_map.py
scholar_flux/api/normalization/pubmed_field_map.py
scholar_flux/api/normalization/springer_nature_field_map.py
scholar_flux/api/providers/__init__.py
scholar_flux/api/providers/arxiv.py
scholar_flux/api/providers/core.py
scholar_flux/api/providers/crossref.py
scholar_flux/api/providers/open_alex.py
scholar_flux/api/providers/plos.py
scholar_flux/api/providers/pubmed.py
scholar_flux/api/providers/pubmed_efetch.py
scholar_flux/api/providers/springer_nature.py
scholar_flux/api/rate_limiting/__init__.py
scholar_flux/api/rate_limiting/rate_limiter.py
scholar_flux/api/rate_limiting/retry_handler.py
scholar_flux/api/rate_limiting/threaded_rate_limiter.py
scholar_flux-0.3.1.dist-info/METADATA
scholar_flux-0.3.1.dist-info/WHEEL
scholar_flux-0.3.1.dist-info/licenses/LICENSE
scholar_flux-0.3.1.dist-info/licenses/NOTICE
scholar_flux-0.3.1.dist-info/RECORD
