Metadata-Version: 2.4
Name: scholar-flux
Version: 0.3.1
Summary: The ScholarFlux API is an open-source project designed to streamline access to academic and scholarly resources across various platforms for discovery and analyses. It offers a unified API that simplifies querying academic databases, retrieving metadata, and performing comprehensive searches within scholarly articles, journals, and publications.
License: Apache-2.0
License-File: LICENSE
License-File: NOTICE
Author: Sammie L. Haskin
Author-email: 44345113+SammieH21@users.noreply.github.com
Requires-Python: >=3.10
Classifier: License :: OSI Approved :: Apache Software License
Classifier: Programming Language :: Python :: 3
Classifier: Programming Language :: Python :: 3.10
Classifier: Programming Language :: Python :: 3.11
Classifier: Programming Language :: Python :: 3.12
Classifier: Programming Language :: Python :: 3.13
Classifier: Programming Language :: Python :: 3.14
Provides-Extra: cryptography
Provides-Extra: database
Provides-Extra: parsing
Requires-Dist: cryptography (>=3.0.0) ; extra == "cryptography"
Requires-Dist: pydantic (>=2.10.6,<3.0.0)
Requires-Dist: pymongo (>=4.0.0) ; extra == "database"
Requires-Dist: python-dotenv (>=0.15.0)
Requires-Dist: pyyaml (>=5.0.0) ; extra == "parsing"
Requires-Dist: redis (>=4.0.0) ; extra == "database"
Requires-Dist: requests (>=2.25.0,<3.0.0)
Requires-Dist: requests-cache[security] (>=1.2.0,<2.0.0)
Requires-Dist: sqlalchemy (>=2.0.0) ; extra == "database"
Requires-Dist: xmltodict (>=0.12.0) ; extra == "parsing"
